<?xml version="1.0" encoding="UTF-8"?>
<?xml-stylesheet href="CoreNLP-to-HTML.xsl" type="text/xsl"?>
<root>
  <document>
    <sentences>
      <sentence id="1">
        <tokens>
          <token id="1">
            <word>Kuwait</word>
            <lemma>Kuwait</lemma>
            <CharacterOffsetBegin>0</CharacterOffsetBegin>
            <CharacterOffsetEnd>6</CharacterOffsetEnd>
            <POS>NNP</POS>
          </token>
          <token id="2">
            <word>'s</word>
            <lemma>'s</lemma>
            <CharacterOffsetBegin>6</CharacterOffsetBegin>
            <CharacterOffsetEnd>8</CharacterOffsetEnd>
            <POS>POS</POS>
          </token>
          <token id="3">
            <word>oil</word>
            <lemma>oil</lemma>
            <CharacterOffsetBegin>9</CharacterOffsetBegin>
            <CharacterOffsetEnd>12</CharacterOffsetEnd>
            <POS>NN</POS>
          </token>
          <token id="4">
            <word>minister</word>
            <lemma>minister</lemma>
            <CharacterOffsetBegin>13</CharacterOffsetBegin>
            <CharacterOffsetEnd>21</CharacterOffsetEnd>
            <POS>NN</POS>
          </token>
          <token id="5">
            <word>said</word>
            <lemma>say</lemma>
            <CharacterOffsetBegin>22</CharacterOffsetBegin>
            <CharacterOffsetEnd>26</CharacterOffsetEnd>
            <POS>VBD</POS>
          </token>
          <token id="6">
            <word>in</word>
            <lemma>in</lemma>
            <CharacterOffsetBegin>27</CharacterOffsetBegin>
            <CharacterOffsetEnd>29</CharacterOffsetEnd>
            <POS>IN</POS>
          </token>
          <token id="7">
            <word>a</word>
            <lemma>a</lemma>
            <CharacterOffsetBegin>30</CharacterOffsetBegin>
            <CharacterOffsetEnd>31</CharacterOffsetEnd>
            <POS>DT</POS>
          </token>
          <token id="8">
            <word>newspaper</word>
            <lemma>newspaper</lemma>
            <CharacterOffsetBegin>32</CharacterOffsetBegin>
            <CharacterOffsetEnd>41</CharacterOffsetEnd>
            <POS>NN</POS>
          </token>
          <token id="9">
            <word>interview</word>
            <lemma>interview</lemma>
            <CharacterOffsetBegin>42</CharacterOffsetBegin>
            <CharacterOffsetEnd>51</CharacterOffsetEnd>
            <POS>NN</POS>
          </token>
          <token id="10">
            <word>that</word>
            <lemma>that</lemma>
            <CharacterOffsetBegin>52</CharacterOffsetBegin>
            <CharacterOffsetEnd>56</CharacterOffsetEnd>
            <POS>IN</POS>
          </token>
          <token id="11">
            <word>there</word>
            <lemma>there</lemma>
            <CharacterOffsetBegin>57</CharacterOffsetBegin>
            <CharacterOffsetEnd>62</CharacterOffsetEnd>
            <POS>EX</POS>
          </token>
          <token id="12">
            <word>were</word>
            <lemma>be</lemma>
            <CharacterOffsetBegin>63</CharacterOffsetBegin>
            <CharacterOffsetEnd>67</CharacterOffsetEnd>
            <POS>VBD</POS>
          </token>
          <token id="13">
            <word>no</word>
            <lemma>no</lemma>
            <CharacterOffsetBegin>68</CharacterOffsetBegin>
            <CharacterOffsetEnd>70</CharacterOffsetEnd>
            <POS>DT</POS>
          </token>
          <token id="14">
            <word>plans</word>
            <lemma>plan</lemma>
            <CharacterOffsetBegin>71</CharacterOffsetBegin>
            <CharacterOffsetEnd>76</CharacterOffsetEnd>
            <POS>NNS</POS>
          </token>
          <token id="15">
            <word>for</word>
            <lemma>for</lemma>
            <CharacterOffsetBegin>77</CharacterOffsetBegin>
            <CharacterOffsetEnd>80</CharacterOffsetEnd>
            <POS>IN</POS>
          </token>
          <token id="16">
            <word>an</word>
            <lemma>a</lemma>
            <CharacterOffsetBegin>81</CharacterOffsetBegin>
            <CharacterOffsetEnd>83</CharacterOffsetEnd>
            <POS>DT</POS>
          </token>
          <token id="17">
            <word>emergency</word>
            <lemma>emergency</lemma>
            <CharacterOffsetBegin>84</CharacterOffsetBegin>
            <CharacterOffsetEnd>93</CharacterOffsetEnd>
            <POS>NN</POS>
          </token>
          <token id="18">
            <word>OPEC</word>
            <lemma>OPEC</lemma>
            <CharacterOffsetBegin>94</CharacterOffsetBegin>
            <CharacterOffsetEnd>98</CharacterOffsetEnd>
            <POS>NNP</POS>
          </token>
          <token id="19">
            <word>meeting</word>
            <lemma>meeting</lemma>
            <CharacterOffsetBegin>99</CharacterOffsetBegin>
            <CharacterOffsetEnd>106</CharacterOffsetEnd>
            <POS>NN</POS>
          </token>
          <token id="20">
            <word>after</word>
            <lemma>after</lemma>
            <CharacterOffsetBegin>107</CharacterOffsetBegin>
            <CharacterOffsetEnd>112</CharacterOffsetEnd>
            <POS>IN</POS>
          </token>
          <token id="21">
            <word>the</word>
            <lemma>the</lemma>
            <CharacterOffsetBegin>113</CharacterOffsetBegin>
            <CharacterOffsetEnd>116</CharacterOffsetEnd>
            <POS>DT</POS>
          </token>
          <token id="22">
            <word>recent</word>
            <lemma>recent</lemma>
            <CharacterOffsetBegin>117</CharacterOffsetBegin>
            <CharacterOffsetEnd>123</CharacterOffsetEnd>
            <POS>JJ</POS>
          </token>
          <token id="23">
            <word>weakness</word>
            <lemma>weakness</lemma>
            <CharacterOffsetBegin>124</CharacterOffsetBegin>
            <CharacterOffsetEnd>132</CharacterOffsetEnd>
            <POS>NN</POS>
          </token>
          <token id="24">
            <word>in</word>
            <lemma>in</lemma>
            <CharacterOffsetBegin>133</CharacterOffsetBegin>
            <CharacterOffsetEnd>135</CharacterOffsetEnd>
            <POS>IN</POS>
          </token>
          <token id="25">
            <word>world</word>
            <lemma>world</lemma>
            <CharacterOffsetBegin>136</CharacterOffsetBegin>
            <CharacterOffsetEnd>141</CharacterOffsetEnd>
            <POS>NN</POS>
          </token>
          <token id="26">
            <word>oil</word>
            <lemma>oil</lemma>
            <CharacterOffsetBegin>142</CharacterOffsetBegin>
            <CharacterOffsetEnd>145</CharacterOffsetEnd>
            <POS>NN</POS>
          </token>
          <token id="27">
            <word>prices</word>
            <lemma>price</lemma>
            <CharacterOffsetBegin>146</CharacterOffsetBegin>
            <CharacterOffsetEnd>152</CharacterOffsetEnd>
            <POS>NNS</POS>
          </token>
          <token id="28">
            <word>.</word>
            <lemma>.</lemma>
            <CharacterOffsetBegin>152</CharacterOffsetBegin>
            <CharacterOffsetEnd>153</CharacterOffsetEnd>
            <POS>.</POS>
          </token>
        </tokens>
      </sentence>
      <sentence id="2">
        <tokens>
          <token id="1">
            <word>Sheikh</word>
            <lemma>Sheikh</lemma>
            <CharacterOffsetBegin>158</CharacterOffsetBegin>
            <CharacterOffsetEnd>164</CharacterOffsetEnd>
            <POS>NNP</POS>
          </token>
          <token id="2">
            <word>Ali</word>
            <lemma>Ali</lemma>
            <CharacterOffsetBegin>165</CharacterOffsetBegin>
            <CharacterOffsetEnd>168</CharacterOffsetEnd>
            <POS>NNP</POS>
          </token>
          <token id="3">
            <word>al-Khalifa</word>
            <lemma>al-Khalifa</lemma>
            <CharacterOffsetBegin>169</CharacterOffsetBegin>
            <CharacterOffsetEnd>179</CharacterOffsetEnd>
            <POS>NNP</POS>
          </token>
          <token id="4">
            <word>al-Sabah</word>
            <lemma>al-Sabah</lemma>
            <CharacterOffsetBegin>180</CharacterOffsetBegin>
            <CharacterOffsetEnd>188</CharacterOffsetEnd>
            <POS>NNP</POS>
          </token>
          <token id="5">
            <word>was</word>
            <lemma>be</lemma>
            <CharacterOffsetBegin>189</CharacterOffsetBegin>
            <CharacterOffsetEnd>192</CharacterOffsetEnd>
            <POS>VBD</POS>
          </token>
          <token id="6">
            <word>quoted</word>
            <lemma>quote</lemma>
            <CharacterOffsetBegin>193</CharacterOffsetBegin>
            <CharacterOffsetEnd>199</CharacterOffsetEnd>
            <POS>VBN</POS>
          </token>
          <token id="7">
            <word>by</word>
            <lemma>by</lemma>
            <CharacterOffsetBegin>200</CharacterOffsetBegin>
            <CharacterOffsetEnd>202</CharacterOffsetEnd>
            <POS>IN</POS>
          </token>
          <token id="8">
            <word>the</word>
            <lemma>the</lemma>
            <CharacterOffsetBegin>203</CharacterOffsetBegin>
            <CharacterOffsetEnd>206</CharacterOffsetEnd>
            <POS>DT</POS>
          </token>
          <token id="9">
            <word>local</word>
            <lemma>local</lemma>
            <CharacterOffsetBegin>207</CharacterOffsetBegin>
            <CharacterOffsetEnd>212</CharacterOffsetEnd>
            <POS>JJ</POS>
          </token>
          <token id="10">
            <word>daily</word>
            <lemma>daily</lemma>
            <CharacterOffsetBegin>213</CharacterOffsetBegin>
            <CharacterOffsetEnd>218</CharacterOffsetEnd>
            <POS>JJ</POS>
          </token>
          <token id="11">
            <word>al-Qabas</word>
            <lemma>al-qaba</lemma>
            <CharacterOffsetBegin>219</CharacterOffsetBegin>
            <CharacterOffsetEnd>227</CharacterOffsetEnd>
            <POS>NNS</POS>
          </token>
          <token id="12">
            <word>as</word>
            <lemma>as</lemma>
            <CharacterOffsetBegin>228</CharacterOffsetBegin>
            <CharacterOffsetEnd>230</CharacterOffsetEnd>
            <POS>IN</POS>
          </token>
          <token id="13">
            <word>saying</word>
            <lemma>say</lemma>
            <CharacterOffsetBegin>231</CharacterOffsetBegin>
            <CharacterOffsetEnd>237</CharacterOffsetEnd>
            <POS>VBG</POS>
          </token>
          <token id="14">
            <word>that</word>
            <lemma>that</lemma>
            <CharacterOffsetBegin>238</CharacterOffsetBegin>
            <CharacterOffsetEnd>242</CharacterOffsetEnd>
            <POS>IN</POS>
          </token>
          <token id="15">
            <word>``</word>
            <lemma>``</lemma>
            <CharacterOffsetBegin>243</CharacterOffsetBegin>
            <CharacterOffsetEnd>244</CharacterOffsetEnd>
            <POS>``</POS>
          </token>
          <token id="16">
            <word>none</word>
            <lemma>none</lemma>
            <CharacterOffsetBegin>244</CharacterOffsetBegin>
            <CharacterOffsetEnd>248</CharacterOffsetEnd>
            <POS>NN</POS>
          </token>
          <token id="17">
            <word>of</word>
            <lemma>of</lemma>
            <CharacterOffsetBegin>249</CharacterOffsetBegin>
            <CharacterOffsetEnd>251</CharacterOffsetEnd>
            <POS>IN</POS>
          </token>
          <token id="18">
            <word>the</word>
            <lemma>the</lemma>
            <CharacterOffsetBegin>252</CharacterOffsetBegin>
            <CharacterOffsetEnd>255</CharacterOffsetEnd>
            <POS>DT</POS>
          </token>
          <token id="19">
            <word>OPEC</word>
            <lemma>OPEC</lemma>
            <CharacterOffsetBegin>256</CharacterOffsetBegin>
            <CharacterOffsetEnd>260</CharacterOffsetEnd>
            <POS>NNP</POS>
          </token>
          <token id="20">
            <word>members</word>
            <lemma>member</lemma>
            <CharacterOffsetBegin>261</CharacterOffsetBegin>
            <CharacterOffsetEnd>268</CharacterOffsetEnd>
            <POS>NNS</POS>
          </token>
          <token id="21">
            <word>has</word>
            <lemma>have</lemma>
            <CharacterOffsetBegin>269</CharacterOffsetBegin>
            <CharacterOffsetEnd>272</CharacterOffsetEnd>
            <POS>VBZ</POS>
          </token>
          <token id="22">
            <word>asked</word>
            <lemma>ask</lemma>
            <CharacterOffsetBegin>273</CharacterOffsetBegin>
            <CharacterOffsetEnd>278</CharacterOffsetEnd>
            <POS>VBN</POS>
          </token>
          <token id="23">
            <word>for</word>
            <lemma>for</lemma>
            <CharacterOffsetBegin>279</CharacterOffsetBegin>
            <CharacterOffsetEnd>282</CharacterOffsetEnd>
            <POS>IN</POS>
          </token>
          <token id="24">
            <word>such</word>
            <lemma>such</lemma>
            <CharacterOffsetBegin>283</CharacterOffsetBegin>
            <CharacterOffsetEnd>287</CharacterOffsetEnd>
            <POS>JJ</POS>
          </token>
          <token id="25">
            <word>a</word>
            <lemma>a</lemma>
            <CharacterOffsetBegin>288</CharacterOffsetBegin>
            <CharacterOffsetEnd>289</CharacterOffsetEnd>
            <POS>DT</POS>
          </token>
          <token id="26">
            <word>meeting</word>
            <lemma>meeting</lemma>
            <CharacterOffsetBegin>290</CharacterOffsetBegin>
            <CharacterOffsetEnd>297</CharacterOffsetEnd>
            <POS>NN</POS>
          </token>
          <token id="27">
            <word>.</word>
            <lemma>.</lemma>
            <CharacterOffsetBegin>297</CharacterOffsetBegin>
            <CharacterOffsetEnd>298</CharacterOffsetEnd>
            <POS>.</POS>
          </token>
          <token id="28">
            <word>''</word>
            <lemma>''</lemma>
            <CharacterOffsetBegin>298</CharacterOffsetBegin>
            <CharacterOffsetEnd>299</CharacterOffsetEnd>
            <POS>''</POS>
          </token>
        </tokens>
      </sentence>
      <sentence id="3">
        <tokens>
          <token id="1">
            <word>He</word>
            <lemma>he</lemma>
            <CharacterOffsetBegin>304</CharacterOffsetBegin>
            <CharacterOffsetEnd>306</CharacterOffsetEnd>
            <POS>PRP</POS>
          </token>
          <token id="2">
            <word>also</word>
            <lemma>also</lemma>
            <CharacterOffsetBegin>307</CharacterOffsetBegin>
            <CharacterOffsetEnd>311</CharacterOffsetEnd>
            <POS>RB</POS>
          </token>
          <token id="3">
            <word>denied</word>
            <lemma>deny</lemma>
            <CharacterOffsetBegin>312</CharacterOffsetBegin>
            <CharacterOffsetEnd>318</CharacterOffsetEnd>
            <POS>VBD</POS>
          </token>
          <token id="4">
            <word>that</word>
            <lemma>that</lemma>
            <CharacterOffsetBegin>319</CharacterOffsetBegin>
            <CharacterOffsetEnd>323</CharacterOffsetEnd>
            <POS>IN</POS>
          </token>
          <token id="5">
            <word>Kuwait</word>
            <lemma>Kuwait</lemma>
            <CharacterOffsetBegin>324</CharacterOffsetBegin>
            <CharacterOffsetEnd>330</CharacterOffsetEnd>
            <POS>NNP</POS>
          </token>
          <token id="6">
            <word>was</word>
            <lemma>be</lemma>
            <CharacterOffsetBegin>331</CharacterOffsetBegin>
            <CharacterOffsetEnd>334</CharacterOffsetEnd>
            <POS>VBD</POS>
          </token>
          <token id="7">
            <word>pumping</word>
            <lemma>pump</lemma>
            <CharacterOffsetBegin>335</CharacterOffsetBegin>
            <CharacterOffsetEnd>342</CharacterOffsetEnd>
            <POS>VBG</POS>
          </token>
          <token id="8">
            <word>above</word>
            <lemma>above</lemma>
            <CharacterOffsetBegin>343</CharacterOffsetBegin>
            <CharacterOffsetEnd>348</CharacterOffsetEnd>
            <POS>IN</POS>
          </token>
          <token id="9">
            <word>its</word>
            <lemma>its</lemma>
            <CharacterOffsetBegin>349</CharacterOffsetBegin>
            <CharacterOffsetEnd>352</CharacterOffsetEnd>
            <POS>PRP$</POS>
          </token>
          <token id="10">
            <word>OPEC</word>
            <lemma>OPEC</lemma>
            <CharacterOffsetBegin>353</CharacterOffsetBegin>
            <CharacterOffsetEnd>357</CharacterOffsetEnd>
            <POS>NNP</POS>
          </token>
          <token id="11">
            <word>quota</word>
            <lemma>quota</lemma>
            <CharacterOffsetBegin>358</CharacterOffsetBegin>
            <CharacterOffsetEnd>363</CharacterOffsetEnd>
            <POS>NN</POS>
          </token>
          <token id="12">
            <word>of</word>
            <lemma>of</lemma>
            <CharacterOffsetBegin>364</CharacterOffsetBegin>
            <CharacterOffsetEnd>366</CharacterOffsetEnd>
            <POS>IN</POS>
          </token>
          <token id="13">
            <word>948,000</word>
            <lemma>948,000</lemma>
            <CharacterOffsetBegin>367</CharacterOffsetBegin>
            <CharacterOffsetEnd>374</CharacterOffsetEnd>
            <POS>CD</POS>
          </token>
          <token id="14">
            <word>barrels</word>
            <lemma>barrel</lemma>
            <CharacterOffsetBegin>375</CharacterOffsetBegin>
            <CharacterOffsetEnd>382</CharacterOffsetEnd>
            <POS>NNS</POS>
          </token>
          <token id="15">
            <word>of</word>
            <lemma>of</lemma>
            <CharacterOffsetBegin>383</CharacterOffsetBegin>
            <CharacterOffsetEnd>385</CharacterOffsetEnd>
            <POS>IN</POS>
          </token>
          <token id="16">
            <word>crude</word>
            <lemma>crude</lemma>
            <CharacterOffsetBegin>386</CharacterOffsetBegin>
            <CharacterOffsetEnd>391</CharacterOffsetEnd>
            <POS>JJ</POS>
          </token>
          <token id="17">
            <word>daily</word>
            <lemma>daily</lemma>
            <CharacterOffsetBegin>392</CharacterOffsetBegin>
            <CharacterOffsetEnd>397</CharacterOffsetEnd>
            <POS>JJ</POS>
          </token>
          <token id="18">
            <word>-LRB-</word>
            <lemma>-lrb-</lemma>
            <CharacterOffsetBegin>398</CharacterOffsetBegin>
            <CharacterOffsetEnd>399</CharacterOffsetEnd>
            <POS>-LRB-</POS>
          </token>
          <token id="19">
            <word>bpd</word>
            <lemma>bpd</lemma>
            <CharacterOffsetBegin>399</CharacterOffsetBegin>
            <CharacterOffsetEnd>402</CharacterOffsetEnd>
            <POS>NN</POS>
          </token>
          <token id="20">
            <word>-RRB-</word>
            <lemma>-rrb-</lemma>
            <CharacterOffsetBegin>402</CharacterOffsetBegin>
            <CharacterOffsetEnd>403</CharacterOffsetEnd>
            <POS>-RRB-</POS>
          </token>
          <token id="21">
            <word>.</word>
            <lemma>.</lemma>
            <CharacterOffsetBegin>403</CharacterOffsetBegin>
            <CharacterOffsetEnd>404</CharacterOffsetEnd>
            <POS>.</POS>
          </token>
        </tokens>
      </sentence>
      <sentence id="4">
        <tokens>
          <token id="1">
            <word>Crude</word>
            <lemma>crude</lemma>
            <CharacterOffsetBegin>409</CharacterOffsetBegin>
            <CharacterOffsetEnd>414</CharacterOffsetEnd>
            <POS>JJ</POS>
          </token>
          <token id="2">
            <word>oil</word>
            <lemma>oil</lemma>
            <CharacterOffsetBegin>415</CharacterOffsetBegin>
            <CharacterOffsetEnd>418</CharacterOffsetEnd>
            <POS>NN</POS>
          </token>
          <token id="3">
            <word>prices</word>
            <lemma>price</lemma>
            <CharacterOffsetBegin>419</CharacterOffsetBegin>
            <CharacterOffsetEnd>425</CharacterOffsetEnd>
            <POS>NNS</POS>
          </token>
          <token id="4">
            <word>fell</word>
            <lemma>fall</lemma>
            <CharacterOffsetBegin>426</CharacterOffsetBegin>
            <CharacterOffsetEnd>430</CharacterOffsetEnd>
            <POS>VBD</POS>
          </token>
          <token id="5">
            <word>sharply</word>
            <lemma>sharply</lemma>
            <CharacterOffsetBegin>431</CharacterOffsetBegin>
            <CharacterOffsetEnd>438</CharacterOffsetEnd>
            <POS>RB</POS>
          </token>
          <token id="6">
            <word>last</word>
            <lemma>last</lemma>
            <CharacterOffsetBegin>439</CharacterOffsetBegin>
            <CharacterOffsetEnd>443</CharacterOffsetEnd>
            <POS>JJ</POS>
          </token>
          <token id="7">
            <word>week</word>
            <lemma>week</lemma>
            <CharacterOffsetBegin>444</CharacterOffsetBegin>
            <CharacterOffsetEnd>448</CharacterOffsetEnd>
            <POS>NN</POS>
          </token>
          <token id="8">
            <word>as</word>
            <lemma>as</lemma>
            <CharacterOffsetBegin>449</CharacterOffsetBegin>
            <CharacterOffsetEnd>451</CharacterOffsetEnd>
            <POS>IN</POS>
          </token>
          <token id="9">
            <word>international</word>
            <lemma>international</lemma>
            <CharacterOffsetBegin>452</CharacterOffsetBegin>
            <CharacterOffsetEnd>465</CharacterOffsetEnd>
            <POS>JJ</POS>
          </token>
          <token id="10">
            <word>oil</word>
            <lemma>oil</lemma>
            <CharacterOffsetBegin>466</CharacterOffsetBegin>
            <CharacterOffsetEnd>469</CharacterOffsetEnd>
            <POS>NN</POS>
          </token>
          <token id="11">
            <word>traders</word>
            <lemma>trader</lemma>
            <CharacterOffsetBegin>470</CharacterOffsetBegin>
            <CharacterOffsetEnd>477</CharacterOffsetEnd>
            <POS>NNS</POS>
          </token>
          <token id="12">
            <word>and</word>
            <lemma>and</lemma>
            <CharacterOffsetBegin>478</CharacterOffsetBegin>
            <CharacterOffsetEnd>481</CharacterOffsetEnd>
            <POS>CC</POS>
          </token>
          <token id="13">
            <word>analysts</word>
            <lemma>analyst</lemma>
            <CharacterOffsetBegin>482</CharacterOffsetBegin>
            <CharacterOffsetEnd>490</CharacterOffsetEnd>
            <POS>NNS</POS>
          </token>
          <token id="14">
            <word>estimated</word>
            <lemma>estimate</lemma>
            <CharacterOffsetBegin>491</CharacterOffsetBegin>
            <CharacterOffsetEnd>500</CharacterOffsetEnd>
            <POS>VBD</POS>
          </token>
          <token id="15">
            <word>the</word>
            <lemma>the</lemma>
            <CharacterOffsetBegin>501</CharacterOffsetBegin>
            <CharacterOffsetEnd>504</CharacterOffsetEnd>
            <POS>DT</POS>
          </token>
          <token id="16">
            <word>13-nation</word>
            <lemma>13-nation</lemma>
            <CharacterOffsetBegin>505</CharacterOffsetBegin>
            <CharacterOffsetEnd>514</CharacterOffsetEnd>
            <POS>JJ</POS>
          </token>
          <token id="17">
            <word>OPEC</word>
            <lemma>OPEC</lemma>
            <CharacterOffsetBegin>515</CharacterOffsetBegin>
            <CharacterOffsetEnd>519</CharacterOffsetEnd>
            <POS>NNP</POS>
          </token>
          <token id="18">
            <word>was</word>
            <lemma>be</lemma>
            <CharacterOffsetBegin>520</CharacterOffsetBegin>
            <CharacterOffsetEnd>523</CharacterOffsetEnd>
            <POS>VBD</POS>
          </token>
          <token id="19">
            <word>pumping</word>
            <lemma>pump</lemma>
            <CharacterOffsetBegin>524</CharacterOffsetBegin>
            <CharacterOffsetEnd>531</CharacterOffsetEnd>
            <POS>VBG</POS>
          </token>
          <token id="20">
            <word>up</word>
            <lemma>up</lemma>
            <CharacterOffsetBegin>532</CharacterOffsetBegin>
            <CharacterOffsetEnd>534</CharacterOffsetEnd>
            <POS>RP</POS>
          </token>
          <token id="21">
            <word>to</word>
            <lemma>to</lemma>
            <CharacterOffsetBegin>535</CharacterOffsetBegin>
            <CharacterOffsetEnd>537</CharacterOffsetEnd>
            <POS>TO</POS>
          </token>
          <token id="22">
            <word>one</word>
            <lemma>one</lemma>
            <CharacterOffsetBegin>538</CharacterOffsetBegin>
            <CharacterOffsetEnd>541</CharacterOffsetEnd>
            <POS>CD</POS>
          </token>
          <token id="23">
            <word>million</word>
            <lemma>million</lemma>
            <CharacterOffsetBegin>542</CharacterOffsetBegin>
            <CharacterOffsetEnd>549</CharacterOffsetEnd>
            <POS>CD</POS>
          </token>
          <token id="24">
            <word>bpd</word>
            <lemma>bpd</lemma>
            <CharacterOffsetBegin>550</CharacterOffsetBegin>
            <CharacterOffsetEnd>553</CharacterOffsetEnd>
            <POS>NN</POS>
          </token>
          <token id="25">
            <word>over</word>
            <lemma>over</lemma>
            <CharacterOffsetBegin>554</CharacterOffsetBegin>
            <CharacterOffsetEnd>558</CharacterOffsetEnd>
            <POS>IN</POS>
          </token>
          <token id="26">
            <word>its</word>
            <lemma>its</lemma>
            <CharacterOffsetBegin>559</CharacterOffsetBegin>
            <CharacterOffsetEnd>562</CharacterOffsetEnd>
            <POS>PRP$</POS>
          </token>
          <token id="27">
            <word>self-imposed</word>
            <lemma>self-imposed</lemma>
            <CharacterOffsetBegin>563</CharacterOffsetBegin>
            <CharacterOffsetEnd>575</CharacterOffsetEnd>
            <POS>JJ</POS>
          </token>
          <token id="28">
            <word>limits</word>
            <lemma>limit</lemma>
            <CharacterOffsetBegin>576</CharacterOffsetBegin>
            <CharacterOffsetEnd>582</CharacterOffsetEnd>
            <POS>NNS</POS>
          </token>
          <token id="29">
            <word>.</word>
            <lemma>.</lemma>
            <CharacterOffsetBegin>582</CharacterOffsetBegin>
            <CharacterOffsetEnd>583</CharacterOffsetEnd>
            <POS>.</POS>
          </token>
        </tokens>
      </sentence>
      <sentence id="5">
        <tokens>
          <token id="1">
            <word>Reuter</word>
            <lemma>Reuter</lemma>
            <CharacterOffsetBegin>585</CharacterOffsetBegin>
            <CharacterOffsetEnd>591</CharacterOffsetEnd>
            <POS>NNP</POS>
          </token>
          <token id="2">
            <word>3</word>
            <lemma>3</lemma>
            <CharacterOffsetBegin>592</CharacterOffsetBegin>
            <CharacterOffsetEnd>593</CharacterOffsetEnd>
            <POS>CD</POS>
          </token>
          <token id="3">
            <word>;</word>
            <lemma>;</lemma>
            <CharacterOffsetBegin>593</CharacterOffsetBegin>
            <CharacterOffsetEnd>594</CharacterOffsetEnd>
            <POS>:</POS>
          </token>
        </tokens>
      </sentence>
    </sentences>
  </document>
</root>
