<?xml version="1.0" encoding="UTF-8"?>
<?xml-stylesheet href="CoreNLP-to-HTML.xsl" type="text/xsl"?>
<root>
  <document>
    <sentences>
      <sentence id="1">
        <tokens>
          <token id="1">
            <word>Shr</word>
            <lemma>Shr</lemma>
            <CharacterOffsetBegin>0</CharacterOffsetBegin>
            <CharacterOffsetEnd>3</CharacterOffsetEnd>
            <POS>NNP</POS>
          </token>
          <token id="2">
            <word>73</word>
            <lemma>73</lemma>
            <CharacterOffsetBegin>4</CharacterOffsetBegin>
            <CharacterOffsetEnd>6</CharacterOffsetEnd>
            <POS>CD</POS>
          </token>
          <token id="3">
            <word>cts</word>
            <lemma>ct</lemma>
            <CharacterOffsetBegin>7</CharacterOffsetBegin>
            <CharacterOffsetEnd>10</CharacterOffsetEnd>
            <POS>NNS</POS>
          </token>
          <token id="4">
            <word>vs</word>
            <lemma>vs</lemma>
            <CharacterOffsetBegin>11</CharacterOffsetBegin>
            <CharacterOffsetEnd>13</CharacterOffsetEnd>
            <POS>CC</POS>
          </token>
          <token id="5">
            <word>58</word>
            <lemma>58</lemma>
            <CharacterOffsetBegin>14</CharacterOffsetBegin>
            <CharacterOffsetEnd>16</CharacterOffsetEnd>
            <POS>CD</POS>
          </token>
          <token id="6">
            <word>cts</word>
            <lemma>ct</lemma>
            <CharacterOffsetBegin>17</CharacterOffsetBegin>
            <CharacterOffsetEnd>20</CharacterOffsetEnd>
            <POS>NNS</POS>
          </token>
          <token id="7">
            <word>Shr</word>
            <lemma>Shr</lemma>
            <CharacterOffsetBegin>25</CharacterOffsetBegin>
            <CharacterOffsetEnd>28</CharacterOffsetEnd>
            <POS>NNP</POS>
          </token>
          <token id="8">
            <word>diluted</word>
            <lemma>dilute</lemma>
            <CharacterOffsetBegin>29</CharacterOffsetBegin>
            <CharacterOffsetEnd>36</CharacterOffsetEnd>
            <POS>VBD</POS>
          </token>
          <token id="9">
            <word>69</word>
            <lemma>69</lemma>
            <CharacterOffsetBegin>37</CharacterOffsetBegin>
            <CharacterOffsetEnd>39</CharacterOffsetEnd>
            <POS>CD</POS>
          </token>
          <token id="10">
            <word>cts</word>
            <lemma>ct</lemma>
            <CharacterOffsetBegin>40</CharacterOffsetBegin>
            <CharacterOffsetEnd>43</CharacterOffsetEnd>
            <POS>NNS</POS>
          </token>
          <token id="11">
            <word>vs</word>
            <lemma>vs</lemma>
            <CharacterOffsetBegin>44</CharacterOffsetBegin>
            <CharacterOffsetEnd>46</CharacterOffsetEnd>
            <POS>CC</POS>
          </token>
          <token id="12">
            <word>54</word>
            <lemma>54</lemma>
            <CharacterOffsetBegin>47</CharacterOffsetBegin>
            <CharacterOffsetEnd>49</CharacterOffsetEnd>
            <POS>CD</POS>
          </token>
          <token id="13">
            <word>cts</word>
            <lemma>ct</lemma>
            <CharacterOffsetBegin>50</CharacterOffsetBegin>
            <CharacterOffsetEnd>53</CharacterOffsetEnd>
            <POS>NNS</POS>
          </token>
          <token id="14">
            <word>Net</word>
            <lemma>net</lemma>
            <CharacterOffsetBegin>58</CharacterOffsetBegin>
            <CharacterOffsetEnd>61</CharacterOffsetEnd>
            <POS>JJ</POS>
          </token>
          <token id="15">
            <word>1,101,000</word>
            <lemma>1,101,000</lemma>
            <CharacterOffsetBegin>62</CharacterOffsetBegin>
            <CharacterOffsetEnd>71</CharacterOffsetEnd>
            <POS>CD</POS>
          </token>
          <token id="16">
            <word>vs</word>
            <lemma>vs</lemma>
            <CharacterOffsetBegin>72</CharacterOffsetBegin>
            <CharacterOffsetEnd>74</CharacterOffsetEnd>
            <POS>CC</POS>
          </token>
          <token id="17">
            <word>901,000</word>
            <lemma>901,000</lemma>
            <CharacterOffsetBegin>75</CharacterOffsetBegin>
            <CharacterOffsetEnd>82</CharacterOffsetEnd>
            <POS>CD</POS>
          </token>
          <token id="18">
            <word>33.0</word>
            <lemma>33.0</lemma>
            <CharacterOffsetBegin>87</CharacterOffsetBegin>
            <CharacterOffsetEnd>91</CharacterOffsetEnd>
            <POS>CD</POS>
          </token>
          <token id="19">
            <word>Sales</word>
            <lemma>sale</lemma>
            <CharacterOffsetBegin>91</CharacterOffsetBegin>
            <CharacterOffsetEnd>96</CharacterOffsetEnd>
            <POS>NNS</POS>
          </token>
          <token id="20">
            <word>m29</word>
            <lemma>m29</lemma>
            <CharacterOffsetBegin>98</CharacterOffsetBegin>
            <CharacterOffsetEnd>101</CharacterOffsetEnd>
            <POS>NN</POS>
          </token>
          <token id="21">
            <word>.1</word>
            <lemma>.1</lemma>
            <CharacterOffsetBegin>101</CharacterOffsetBegin>
            <CharacterOffsetEnd>103</CharacterOffsetEnd>
            <POS>CD</POS>
          </token>
          <token id="22">
            <word>ln</word>
            <lemma>ln</lemma>
            <CharacterOffsetBegin>103</CharacterOffsetBegin>
            <CharacterOffsetEnd>105</CharacterOffsetEnd>
            <POS>NN</POS>
          </token>
          <token id="23">
            <word>vs</word>
            <lemma>vs</lemma>
            <CharacterOffsetBegin>106</CharacterOffsetBegin>
            <CharacterOffsetEnd>108</CharacterOffsetEnd>
            <POS>CC</POS>
          </token>
          <token id="24">
            <word>mln</word>
            <lemma>mln</lemma>
            <CharacterOffsetBegin>110</CharacterOffsetBegin>
            <CharacterOffsetEnd>113</CharacterOffsetEnd>
            <POS>NN</POS>
          </token>
          <token id="25">
            <word>NOTE</word>
            <lemma>note</lemma>
            <CharacterOffsetBegin>118</CharacterOffsetBegin>
            <CharacterOffsetEnd>122</CharacterOffsetEnd>
            <POS>VBP</POS>
          </token>
          <token id="26">
            <word>:</word>
            <lemma>:</lemma>
            <CharacterOffsetBegin>122</CharacterOffsetBegin>
            <CharacterOffsetEnd>123</CharacterOffsetEnd>
            <POS>:</POS>
          </token>
          <token id="27">
            <word>Results</word>
            <lemma>result</lemma>
            <CharacterOffsetBegin>124</CharacterOffsetBegin>
            <CharacterOffsetEnd>131</CharacterOffsetEnd>
            <POS>NNS</POS>
          </token>
          <token id="28">
            <word>include</word>
            <lemma>include</lemma>
            <CharacterOffsetBegin>132</CharacterOffsetBegin>
            <CharacterOffsetEnd>139</CharacterOffsetEnd>
            <POS>VBP</POS>
          </token>
          <token id="29">
            <word>BMD</word>
            <lemma>bmd</lemma>
            <CharacterOffsetBegin>140</CharacterOffsetBegin>
            <CharacterOffsetEnd>143</CharacterOffsetEnd>
            <POS>NN</POS>
          </token>
          <token id="30">
            <word>of</word>
            <lemma>of</lemma>
            <CharacterOffsetBegin>144</CharacterOffsetBegin>
            <CharacterOffsetEnd>146</CharacterOffsetEnd>
            <POS>IN</POS>
          </token>
          <token id="31">
            <word>New</word>
            <lemma>New</lemma>
            <CharacterOffsetBegin>147</CharacterOffsetBegin>
            <CharacterOffsetEnd>150</CharacterOffsetEnd>
            <POS>NNP</POS>
          </token>
          <token id="32">
            <word>England</word>
            <lemma>England</lemma>
            <CharacterOffsetBegin>151</CharacterOffsetBegin>
            <CharacterOffsetEnd>158</CharacterOffsetEnd>
            <POS>NNP</POS>
          </token>
          <token id="33">
            <word>Inc</word>
            <lemma>Inc</lemma>
            <CharacterOffsetBegin>159</CharacterOffsetBegin>
            <CharacterOffsetEnd>162</CharacterOffsetEnd>
            <POS>NNP</POS>
          </token>
          <token id="34">
            <word>from</word>
            <lemma>from</lemma>
            <CharacterOffsetBegin>163</CharacterOffsetBegin>
            <CharacterOffsetEnd>167</CharacterOffsetEnd>
            <POS>IN</POS>
          </token>
          <token id="35">
            <word>September</word>
            <lemma>September</lemma>
            <CharacterOffsetBegin>168</CharacterOffsetBegin>
            <CharacterOffsetEnd>177</CharacterOffsetEnd>
            <POS>NNP</POS>
          </token>
          <token id="36">
            <word>1</word>
            <lemma>1</lemma>
            <CharacterOffsetBegin>178</CharacterOffsetBegin>
            <CharacterOffsetEnd>179</CharacterOffsetEnd>
            <POS>CD</POS>
          </token>
          <token id="37">
            <word>,</word>
            <lemma>,</lemma>
            <CharacterOffsetBegin>179</CharacterOffsetBegin>
            <CharacterOffsetEnd>180</CharacterOffsetEnd>
            <POS>,</POS>
          </token>
          <token id="38">
            <word>1986</word>
            <lemma>1986</lemma>
            <CharacterOffsetBegin>181</CharacterOffsetBegin>
            <CharacterOffsetEnd>185</CharacterOffsetEnd>
            <POS>CD</POS>
          </token>
          <token id="39">
            <word>purchase</word>
            <lemma>purchase</lemma>
            <CharacterOffsetBegin>186</CharacterOffsetBegin>
            <CharacterOffsetEnd>194</CharacterOffsetEnd>
            <POS>NN</POS>
          </token>
          <token id="40">
            <word>.</word>
            <lemma>.</lemma>
            <CharacterOffsetBegin>194</CharacterOffsetBegin>
            <CharacterOffsetEnd>195</CharacterOffsetEnd>
            <POS>.</POS>
          </token>
        </tokens>
      </sentence>
      <sentence id="2">
        <tokens>
          <token id="1">
            <word>Reuter</word>
            <lemma>Reuter</lemma>
            <CharacterOffsetBegin>197</CharacterOffsetBegin>
            <CharacterOffsetEnd>203</CharacterOffsetEnd>
            <POS>NNP</POS>
          </token>
          <token id="2">
            <word>3</word>
            <lemma>3</lemma>
            <CharacterOffsetBegin>204</CharacterOffsetBegin>
            <CharacterOffsetEnd>205</CharacterOffsetEnd>
            <POS>CD</POS>
          </token>
          <token id="3">
            <word>;</word>
            <lemma>;</lemma>
            <CharacterOffsetBegin>205</CharacterOffsetBegin>
            <CharacterOffsetEnd>206</CharacterOffsetEnd>
            <POS>:</POS>
          </token>
        </tokens>
      </sentence>
    </sentences>
  </document>
</root>
