<?xml version="1.0" encoding="UTF-8"?>
<?xml-stylesheet href="CoreNLP-to-HTML.xsl" type="text/xsl"?>
<root>
  <document>
    <sentences>
      <sentence id="1">
        <tokens>
          <token id="1">
            <word>U.S.</word>
            <lemma>U.S.</lemma>
            <CharacterOffsetBegin>0</CharacterOffsetBegin>
            <CharacterOffsetEnd>4</CharacterOffsetEnd>
            <POS>NNP</POS>
          </token>
          <token id="2">
            <word>Secretary</word>
            <lemma>Secretary</lemma>
            <CharacterOffsetBegin>5</CharacterOffsetBegin>
            <CharacterOffsetEnd>14</CharacterOffsetEnd>
            <POS>NNP</POS>
          </token>
          <token id="3">
            <word>of</word>
            <lemma>of</lemma>
            <CharacterOffsetBegin>15</CharacterOffsetBegin>
            <CharacterOffsetEnd>17</CharacterOffsetEnd>
            <POS>IN</POS>
          </token>
          <token id="4">
            <word>State</word>
            <lemma>State</lemma>
            <CharacterOffsetBegin>18</CharacterOffsetBegin>
            <CharacterOffsetEnd>23</CharacterOffsetEnd>
            <POS>NNP</POS>
          </token>
          <token id="5">
            <word>George</word>
            <lemma>George</lemma>
            <CharacterOffsetBegin>24</CharacterOffsetBegin>
            <CharacterOffsetEnd>30</CharacterOffsetEnd>
            <POS>NNP</POS>
          </token>
          <token id="6">
            <word>Shultz</word>
            <lemma>Shultz</lemma>
            <CharacterOffsetBegin>31</CharacterOffsetBegin>
            <CharacterOffsetEnd>37</CharacterOffsetEnd>
            <POS>NNP</POS>
          </token>
          <token id="7">
            <word>is</word>
            <lemma>be</lemma>
            <CharacterOffsetBegin>38</CharacterOffsetBegin>
            <CharacterOffsetEnd>40</CharacterOffsetEnd>
            <POS>VBZ</POS>
          </token>
          <token id="8">
            <word>likely</word>
            <lemma>likely</lemma>
            <CharacterOffsetBegin>41</CharacterOffsetBegin>
            <CharacterOffsetEnd>47</CharacterOffsetEnd>
            <POS>JJ</POS>
          </token>
          <token id="9">
            <word>to</word>
            <lemma>to</lemma>
            <CharacterOffsetBegin>48</CharacterOffsetBegin>
            <CharacterOffsetEnd>50</CharacterOffsetEnd>
            <POS>TO</POS>
          </token>
          <token id="10">
            <word>visit</word>
            <lemma>visit</lemma>
            <CharacterOffsetBegin>51</CharacterOffsetBegin>
            <CharacterOffsetEnd>56</CharacterOffsetEnd>
            <POS>VB</POS>
          </token>
          <token id="11">
            <word>Moscow</word>
            <lemma>Moscow</lemma>
            <CharacterOffsetBegin>57</CharacterOffsetBegin>
            <CharacterOffsetEnd>63</CharacterOffsetEnd>
            <POS>NNP</POS>
          </token>
          <token id="12">
            <word>soon</word>
            <lemma>soon</lemma>
            <CharacterOffsetBegin>64</CharacterOffsetBegin>
            <CharacterOffsetEnd>68</CharacterOffsetEnd>
            <POS>RB</POS>
          </token>
          <token id="13">
            <word>for</word>
            <lemma>for</lemma>
            <CharacterOffsetBegin>69</CharacterOffsetBegin>
            <CharacterOffsetEnd>72</CharacterOffsetEnd>
            <POS>IN</POS>
          </token>
          <token id="14">
            <word>talks</word>
            <lemma>talk</lemma>
            <CharacterOffsetBegin>73</CharacterOffsetBegin>
            <CharacterOffsetEnd>78</CharacterOffsetEnd>
            <POS>NNS</POS>
          </token>
          <token id="15">
            <word>following</word>
            <lemma>follow</lemma>
            <CharacterOffsetBegin>79</CharacterOffsetBegin>
            <CharacterOffsetEnd>88</CharacterOffsetEnd>
            <POS>VBG</POS>
          </token>
          <token id="16">
            <word>new</word>
            <lemma>new</lemma>
            <CharacterOffsetBegin>89</CharacterOffsetBegin>
            <CharacterOffsetEnd>92</CharacterOffsetEnd>
            <POS>JJ</POS>
          </token>
          <token id="17">
            <word>Soviet</word>
            <lemma>soviet</lemma>
            <CharacterOffsetBegin>93</CharacterOffsetBegin>
            <CharacterOffsetEnd>99</CharacterOffsetEnd>
            <POS>JJ</POS>
          </token>
          <token id="18">
            <word>arms</word>
            <lemma>arm</lemma>
            <CharacterOffsetBegin>100</CharacterOffsetBegin>
            <CharacterOffsetEnd>104</CharacterOffsetEnd>
            <POS>NNS</POS>
          </token>
          <token id="19">
            <word>control</word>
            <lemma>control</lemma>
            <CharacterOffsetBegin>105</CharacterOffsetBegin>
            <CharacterOffsetEnd>112</CharacterOffsetEnd>
            <POS>VBP</POS>
          </token>
          <token id="20">
            <word>proposals</word>
            <lemma>proposal</lemma>
            <CharacterOffsetBegin>113</CharacterOffsetBegin>
            <CharacterOffsetEnd>122</CharacterOffsetEnd>
            <POS>NNS</POS>
          </token>
          <token id="21">
            <word>,</word>
            <lemma>,</lemma>
            <CharacterOffsetBegin>122</CharacterOffsetBegin>
            <CharacterOffsetEnd>123</CharacterOffsetEnd>
            <POS>,</POS>
          </token>
          <token id="22">
            <word>U.S.</word>
            <lemma>U.S.</lemma>
            <CharacterOffsetBegin>124</CharacterOffsetBegin>
            <CharacterOffsetEnd>128</CharacterOffsetEnd>
            <POS>NNP</POS>
          </token>
          <token id="23">
            <word>Officials</word>
            <lemma>Officials</lemma>
            <CharacterOffsetBegin>129</CharacterOffsetBegin>
            <CharacterOffsetEnd>138</CharacterOffsetEnd>
            <POS>NNP</POS>
          </token>
          <token id="24">
            <word>said</word>
            <lemma>say</lemma>
            <CharacterOffsetBegin>139</CharacterOffsetBegin>
            <CharacterOffsetEnd>143</CharacterOffsetEnd>
            <POS>VBD</POS>
          </token>
          <token id="25">
            <word>.</word>
            <lemma>.</lemma>
            <CharacterOffsetBegin>143</CharacterOffsetBegin>
            <CharacterOffsetEnd>144</CharacterOffsetEnd>
            <POS>.</POS>
          </token>
        </tokens>
      </sentence>
      <sentence id="2">
        <tokens>
          <token id="1">
            <word>The</word>
            <lemma>the</lemma>
            <CharacterOffsetBegin>149</CharacterOffsetBegin>
            <CharacterOffsetEnd>152</CharacterOffsetEnd>
            <POS>DT</POS>
          </token>
          <token id="2">
            <word>officials</word>
            <lemma>official</lemma>
            <CharacterOffsetBegin>153</CharacterOffsetBegin>
            <CharacterOffsetEnd>162</CharacterOffsetEnd>
            <POS>NNS</POS>
          </token>
          <token id="3">
            <word>told</word>
            <lemma>tell</lemma>
            <CharacterOffsetBegin>163</CharacterOffsetBegin>
            <CharacterOffsetEnd>167</CharacterOffsetEnd>
            <POS>VBD</POS>
          </token>
          <token id="4">
            <word>Reuters</word>
            <lemma>Reuters</lemma>
            <CharacterOffsetBegin>168</CharacterOffsetBegin>
            <CharacterOffsetEnd>175</CharacterOffsetEnd>
            <POS>NNP</POS>
          </token>
          <token id="5">
            <word>no</word>
            <lemma>no</lemma>
            <CharacterOffsetBegin>176</CharacterOffsetBegin>
            <CharacterOffsetEnd>178</CharacterOffsetEnd>
            <POS>DT</POS>
          </token>
          <token id="6">
            <word>decision</word>
            <lemma>decision</lemma>
            <CharacterOffsetBegin>179</CharacterOffsetBegin>
            <CharacterOffsetEnd>187</CharacterOffsetEnd>
            <POS>NN</POS>
          </token>
          <token id="7">
            <word>had</word>
            <lemma>have</lemma>
            <CharacterOffsetBegin>188</CharacterOffsetBegin>
            <CharacterOffsetEnd>191</CharacterOffsetEnd>
            <POS>VBD</POS>
          </token>
          <token id="8">
            <word>been</word>
            <lemma>be</lemma>
            <CharacterOffsetBegin>192</CharacterOffsetBegin>
            <CharacterOffsetEnd>196</CharacterOffsetEnd>
            <POS>VBN</POS>
          </token>
          <token id="9">
            <word>reached</word>
            <lemma>reach</lemma>
            <CharacterOffsetBegin>197</CharacterOffsetBegin>
            <CharacterOffsetEnd>204</CharacterOffsetEnd>
            <POS>VBN</POS>
          </token>
          <token id="10">
            <word>on</word>
            <lemma>on</lemma>
            <CharacterOffsetBegin>205</CharacterOffsetBegin>
            <CharacterOffsetEnd>207</CharacterOffsetEnd>
            <POS>IN</POS>
          </token>
          <token id="11">
            <word>when</word>
            <lemma>when</lemma>
            <CharacterOffsetBegin>208</CharacterOffsetBegin>
            <CharacterOffsetEnd>212</CharacterOffsetEnd>
            <POS>WRB</POS>
          </token>
          <token id="12">
            <word>the</word>
            <lemma>the</lemma>
            <CharacterOffsetBegin>213</CharacterOffsetBegin>
            <CharacterOffsetEnd>216</CharacterOffsetEnd>
            <POS>DT</POS>
          </token>
          <token id="13">
            <word>trip</word>
            <lemma>trip</lemma>
            <CharacterOffsetBegin>217</CharacterOffsetBegin>
            <CharacterOffsetEnd>221</CharacterOffsetEnd>
            <POS>NN</POS>
          </token>
          <token id="14">
            <word>might</word>
            <lemma>might</lemma>
            <CharacterOffsetBegin>222</CharacterOffsetBegin>
            <CharacterOffsetEnd>227</CharacterOffsetEnd>
            <POS>MD</POS>
          </token>
          <token id="15">
            <word>take</word>
            <lemma>take</lemma>
            <CharacterOffsetBegin>228</CharacterOffsetBegin>
            <CharacterOffsetEnd>232</CharacterOffsetEnd>
            <POS>VB</POS>
          </token>
          <token id="16">
            <word>place</word>
            <lemma>place</lemma>
            <CharacterOffsetBegin>233</CharacterOffsetBegin>
            <CharacterOffsetEnd>238</CharacterOffsetEnd>
            <POS>NN</POS>
          </token>
          <token id="17">
            <word>,</word>
            <lemma>,</lemma>
            <CharacterOffsetBegin>238</CharacterOffsetBegin>
            <CharacterOffsetEnd>239</CharacterOffsetEnd>
            <POS>,</POS>
          </token>
          <token id="18">
            <word>but</word>
            <lemma>but</lemma>
            <CharacterOffsetBegin>240</CharacterOffsetBegin>
            <CharacterOffsetEnd>243</CharacterOffsetEnd>
            <POS>CC</POS>
          </token>
          <token id="19">
            <word>it</word>
            <lemma>it</lemma>
            <CharacterOffsetBegin>244</CharacterOffsetBegin>
            <CharacterOffsetEnd>246</CharacterOffsetEnd>
            <POS>PRP</POS>
          </token>
          <token id="20">
            <word>was</word>
            <lemma>be</lemma>
            <CharacterOffsetBegin>247</CharacterOffsetBegin>
            <CharacterOffsetEnd>250</CharacterOffsetEnd>
            <POS>VBD</POS>
          </token>
          <token id="21">
            <word>likely</word>
            <lemma>likely</lemma>
            <CharacterOffsetBegin>251</CharacterOffsetBegin>
            <CharacterOffsetEnd>257</CharacterOffsetEnd>
            <POS>JJ</POS>
          </token>
          <token id="22">
            <word>to</word>
            <lemma>to</lemma>
            <CharacterOffsetBegin>258</CharacterOffsetBegin>
            <CharacterOffsetEnd>260</CharacterOffsetEnd>
            <POS>TO</POS>
          </token>
          <token id="23">
            <word>be</word>
            <lemma>be</lemma>
            <CharacterOffsetBegin>261</CharacterOffsetBegin>
            <CharacterOffsetEnd>263</CharacterOffsetEnd>
            <POS>VB</POS>
          </token>
          <token id="24">
            <word>within</word>
            <lemma>within</lemma>
            <CharacterOffsetBegin>264</CharacterOffsetBegin>
            <CharacterOffsetEnd>270</CharacterOffsetEnd>
            <POS>IN</POS>
          </token>
          <token id="25">
            <word>a</word>
            <lemma>a</lemma>
            <CharacterOffsetBegin>271</CharacterOffsetBegin>
            <CharacterOffsetEnd>272</CharacterOffsetEnd>
            <POS>DT</POS>
          </token>
          <token id="26">
            <word>month</word>
            <lemma>month</lemma>
            <CharacterOffsetBegin>273</CharacterOffsetBegin>
            <CharacterOffsetEnd>278</CharacterOffsetEnd>
            <POS>NN</POS>
          </token>
          <token id="27">
            <word>.</word>
            <lemma>.</lemma>
            <CharacterOffsetBegin>278</CharacterOffsetBegin>
            <CharacterOffsetEnd>279</CharacterOffsetEnd>
            <POS>.</POS>
          </token>
        </tokens>
      </sentence>
      <sentence id="3">
        <tokens>
          <token id="1">
            <word>Kremlin</word>
            <lemma>Kremlin</lemma>
            <CharacterOffsetBegin>284</CharacterOffsetBegin>
            <CharacterOffsetEnd>291</CharacterOffsetEnd>
            <POS>NNP</POS>
          </token>
          <token id="2">
            <word>leader</word>
            <lemma>leader</lemma>
            <CharacterOffsetBegin>292</CharacterOffsetBegin>
            <CharacterOffsetEnd>298</CharacterOffsetEnd>
            <POS>NN</POS>
          </token>
          <token id="3">
            <word>Mikhail</word>
            <lemma>Mikhail</lemma>
            <CharacterOffsetBegin>299</CharacterOffsetBegin>
            <CharacterOffsetEnd>306</CharacterOffsetEnd>
            <POS>NNP</POS>
          </token>
          <token id="4">
            <word>Gorbachev</word>
            <lemma>Gorbachev</lemma>
            <CharacterOffsetBegin>307</CharacterOffsetBegin>
            <CharacterOffsetEnd>316</CharacterOffsetEnd>
            <POS>NNP</POS>
          </token>
          <token id="5">
            <word>proposed</word>
            <lemma>propose</lemma>
            <CharacterOffsetBegin>317</CharacterOffsetBegin>
            <CharacterOffsetEnd>325</CharacterOffsetEnd>
            <POS>VBD</POS>
          </token>
          <token id="6">
            <word>on</word>
            <lemma>on</lemma>
            <CharacterOffsetBegin>326</CharacterOffsetBegin>
            <CharacterOffsetEnd>328</CharacterOffsetEnd>
            <POS>IN</POS>
          </token>
          <token id="7">
            <word>Saturday</word>
            <lemma>Saturday</lemma>
            <CharacterOffsetBegin>329</CharacterOffsetBegin>
            <CharacterOffsetEnd>337</CharacterOffsetEnd>
            <POS>NNP</POS>
          </token>
          <token id="8">
            <word>that</word>
            <lemma>that</lemma>
            <CharacterOffsetBegin>338</CharacterOffsetBegin>
            <CharacterOffsetEnd>342</CharacterOffsetEnd>
            <POS>WDT</POS>
          </token>
          <token id="9">
            <word>talks</word>
            <lemma>talk</lemma>
            <CharacterOffsetBegin>343</CharacterOffsetBegin>
            <CharacterOffsetEnd>348</CharacterOffsetEnd>
            <POS>VBZ</POS>
          </token>
          <token id="10">
            <word>on</word>
            <lemma>on</lemma>
            <CharacterOffsetBegin>349</CharacterOffsetBegin>
            <CharacterOffsetEnd>351</CharacterOffsetEnd>
            <POS>IN</POS>
          </token>
          <token id="11">
            <word>medium</word>
            <lemma>medium</lemma>
            <CharacterOffsetBegin>352</CharacterOffsetBegin>
            <CharacterOffsetEnd>358</CharacterOffsetEnd>
            <POS>NN</POS>
          </token>
          <token id="12">
            <word>range</word>
            <lemma>range</lemma>
            <CharacterOffsetBegin>359</CharacterOffsetBegin>
            <CharacterOffsetEnd>364</CharacterOffsetEnd>
            <POS>NN</POS>
          </token>
          <token id="13">
            <word>missiles</word>
            <lemma>missile</lemma>
            <CharacterOffsetBegin>365</CharacterOffsetBegin>
            <CharacterOffsetEnd>373</CharacterOffsetEnd>
            <POS>NNS</POS>
          </token>
          <token id="14">
            <word>be</word>
            <lemma>be</lemma>
            <CharacterOffsetBegin>374</CharacterOffsetBegin>
            <CharacterOffsetEnd>376</CharacterOffsetEnd>
            <POS>VB</POS>
          </token>
          <token id="15">
            <word>separated</word>
            <lemma>separate</lemma>
            <CharacterOffsetBegin>377</CharacterOffsetBegin>
            <CharacterOffsetEnd>386</CharacterOffsetEnd>
            <POS>VBN</POS>
          </token>
          <token id="16">
            <word>from</word>
            <lemma>from</lemma>
            <CharacterOffsetBegin>387</CharacterOffsetBegin>
            <CharacterOffsetEnd>391</CharacterOffsetEnd>
            <POS>IN</POS>
          </token>
          <token id="17">
            <word>other</word>
            <lemma>other</lemma>
            <CharacterOffsetBegin>392</CharacterOffsetBegin>
            <CharacterOffsetEnd>397</CharacterOffsetEnd>
            <POS>JJ</POS>
          </token>
          <token id="18">
            <word>arms</word>
            <lemma>arm</lemma>
            <CharacterOffsetBegin>398</CharacterOffsetBegin>
            <CharacterOffsetEnd>402</CharacterOffsetEnd>
            <POS>NNS</POS>
          </token>
          <token id="19">
            <word>issues</word>
            <lemma>issue</lemma>
            <CharacterOffsetBegin>403</CharacterOffsetBegin>
            <CharacterOffsetEnd>409</CharacterOffsetEnd>
            <POS>NNS</POS>
          </token>
          <token id="20">
            <word>.</word>
            <lemma>.</lemma>
            <CharacterOffsetBegin>409</CharacterOffsetBegin>
            <CharacterOffsetEnd>410</CharacterOffsetEnd>
            <POS>.</POS>
          </token>
        </tokens>
      </sentence>
      <sentence id="4">
        <tokens>
          <token id="1">
            <word>Schultz</word>
            <lemma>Schultz</lemma>
            <CharacterOffsetBegin>415</CharacterOffsetBegin>
            <CharacterOffsetEnd>422</CharacterOffsetEnd>
            <POS>NNP</POS>
          </token>
          <token id="2">
            <word>is</word>
            <lemma>be</lemma>
            <CharacterOffsetBegin>423</CharacterOffsetBegin>
            <CharacterOffsetEnd>425</CharacterOffsetEnd>
            <POS>VBZ</POS>
          </token>
          <token id="3">
            <word>currently</word>
            <lemma>currently</lemma>
            <CharacterOffsetBegin>426</CharacterOffsetBegin>
            <CharacterOffsetEnd>435</CharacterOffsetEnd>
            <POS>RB</POS>
          </token>
          <token id="4">
            <word>visiting</word>
            <lemma>visit</lemma>
            <CharacterOffsetBegin>436</CharacterOffsetBegin>
            <CharacterOffsetEnd>444</CharacterOffsetEnd>
            <POS>VBG</POS>
          </token>
          <token id="5">
            <word>Peking</word>
            <lemma>peking</lemma>
            <CharacterOffsetBegin>445</CharacterOffsetBegin>
            <CharacterOffsetEnd>451</CharacterOffsetEnd>
            <POS>JJ</POS>
          </token>
          <token id="6">
            <word>.</word>
            <lemma>.</lemma>
            <CharacterOffsetBegin>451</CharacterOffsetBegin>
            <CharacterOffsetEnd>452</CharacterOffsetEnd>
            <POS>.</POS>
          </token>
        </tokens>
      </sentence>
      <sentence id="5">
        <tokens>
          <token id="1">
            <word>REUTER</word>
            <lemma>reuter</lemma>
            <CharacterOffsetBegin>454</CharacterOffsetBegin>
            <CharacterOffsetEnd>460</CharacterOffsetEnd>
            <POS>NN</POS>
          </token>
          <token id="2">
            <word>3</word>
            <lemma>3</lemma>
            <CharacterOffsetBegin>461</CharacterOffsetBegin>
            <CharacterOffsetEnd>462</CharacterOffsetEnd>
            <POS>CD</POS>
          </token>
          <token id="3">
            <word>;</word>
            <lemma>;</lemma>
            <CharacterOffsetBegin>462</CharacterOffsetBegin>
            <CharacterOffsetEnd>463</CharacterOffsetEnd>
            <POS>:</POS>
          </token>
        </tokens>
      </sentence>
    </sentences>
  </document>
</root>
