<?xml version="1.0" encoding="UTF-8"?>
<?xml-stylesheet href="CoreNLP-to-HTML.xsl" type="text/xsl"?>
<root>
  <document>
    <sentences>
      <sentence id="1">
        <tokens>
          <token id="1">
            <word>Jan</word>
            <lemma>Jan</lemma>
            <CharacterOffsetBegin>0</CharacterOffsetBegin>
            <CharacterOffsetEnd>3</CharacterOffsetEnd>
            <POS>NNP</POS>
          </token>
          <token id="2">
            <word>31</word>
            <lemma>31</lemma>
            <CharacterOffsetBegin>4</CharacterOffsetBegin>
            <CharacterOffsetEnd>6</CharacterOffsetEnd>
            <POS>CD</POS>
          </token>
          <token id="3">
            <word>end</word>
            <lemma>end</lemma>
            <CharacterOffsetBegin>7</CharacterOffsetBegin>
            <CharacterOffsetEnd>10</CharacterOffsetEnd>
            <POS>NN</POS>
          </token>
          <token id="4">
            <word>1.40</word>
            <lemma>1.40</lemma>
            <CharacterOffsetBegin>13</CharacterOffsetBegin>
            <CharacterOffsetEnd>17</CharacterOffsetEnd>
            <POS>CD</POS>
          </token>
          <token id="5">
            <word>Shr</word>
            <lemma>shr</lemma>
            <CharacterOffsetBegin>19</CharacterOffsetBegin>
            <CharacterOffsetEnd>22</CharacterOffsetEnd>
            <POS>NN</POS>
          </token>
          <token id="6">
            <word>dl1</word>
            <lemma>dl1</lemma>
            <CharacterOffsetBegin>24</CharacterOffsetBegin>
            <CharacterOffsetEnd>27</CharacterOffsetEnd>
            <POS>NN</POS>
          </token>
          <token id="7">
            <word>.10</word>
            <lemma>.10</lemma>
            <CharacterOffsetBegin>27</CharacterOffsetBegin>
            <CharacterOffsetEnd>30</CharacterOffsetEnd>
            <POS>CD</POS>
          </token>
          <token id="8">
            <word>rs</word>
            <lemma>r</lemma>
            <CharacterOffsetBegin>30</CharacterOffsetBegin>
            <CharacterOffsetEnd>32</CharacterOffsetEnd>
            <POS>NNS</POS>
          </token>
          <token id="9">
            <word>vs</word>
            <lemma>vs</lemma>
            <CharacterOffsetBegin>33</CharacterOffsetBegin>
            <CharacterOffsetEnd>35</CharacterOffsetEnd>
            <POS>CC</POS>
          </token>
          <token id="10">
            <word>dlrs</word>
            <lemma>dlr</lemma>
            <CharacterOffsetBegin>37</CharacterOffsetBegin>
            <CharacterOffsetEnd>41</CharacterOffsetEnd>
            <POS>NNS</POS>
          </token>
          <token id="11">
            <word>16.4</word>
            <lemma>16.4</lemma>
            <CharacterOffsetBegin>44</CharacterOffsetBegin>
            <CharacterOffsetEnd>48</CharacterOffsetEnd>
            <POS>CD</POS>
          </token>
          <token id="12">
            <word>Net</word>
            <lemma>net</lemma>
            <CharacterOffsetBegin>50</CharacterOffsetBegin>
            <CharacterOffsetEnd>53</CharacterOffsetEnd>
            <POS>JJ</POS>
          </token>
          <token id="13">
            <word>m12</word>
            <lemma>m12</lemma>
            <CharacterOffsetBegin>55</CharacterOffsetBegin>
            <CharacterOffsetEnd>58</CharacterOffsetEnd>
            <POS>NN</POS>
          </token>
          <token id="14">
            <word>.9</word>
            <lemma>.9</lemma>
            <CharacterOffsetBegin>58</CharacterOffsetBegin>
            <CharacterOffsetEnd>60</CharacterOffsetEnd>
            <POS>CD</POS>
          </token>
          <token id="15">
            <word>ln</word>
            <lemma>ln</lemma>
            <CharacterOffsetBegin>60</CharacterOffsetBegin>
            <CharacterOffsetEnd>62</CharacterOffsetEnd>
            <POS>NN</POS>
          </token>
          <token id="16">
            <word>vs</word>
            <lemma>vs</lemma>
            <CharacterOffsetBegin>63</CharacterOffsetBegin>
            <CharacterOffsetEnd>65</CharacterOffsetEnd>
            <POS>CC</POS>
          </token>
          <token id="17">
            <word>mln</word>
            <lemma>mln</lemma>
            <CharacterOffsetBegin>67</CharacterOffsetBegin>
            <CharacterOffsetEnd>70</CharacterOffsetEnd>
            <POS>NN</POS>
          </token>
          <token id="18">
            <word>196.2</word>
            <lemma>196.2</lemma>
            <CharacterOffsetBegin>74</CharacterOffsetBegin>
            <CharacterOffsetEnd>79</CharacterOffsetEnd>
            <POS>CD</POS>
          </token>
          <token id="19">
            <word>Revs</word>
            <lemma>Revs</lemma>
            <CharacterOffsetBegin>80</CharacterOffsetBegin>
            <CharacterOffsetEnd>84</CharacterOffsetEnd>
            <POS>NNP</POS>
          </token>
          <token id="20">
            <word>m157</word>
            <lemma>m157</lemma>
            <CharacterOffsetBegin>86</CharacterOffsetBegin>
            <CharacterOffsetEnd>90</CharacterOffsetEnd>
            <POS>NN</POS>
          </token>
          <token id="21">
            <word>.5</word>
            <lemma>.5</lemma>
            <CharacterOffsetBegin>90</CharacterOffsetBegin>
            <CharacterOffsetEnd>92</CharacterOffsetEnd>
            <POS>CD</POS>
          </token>
          <token id="22">
            <word>ln</word>
            <lemma>ln</lemma>
            <CharacterOffsetBegin>92</CharacterOffsetBegin>
            <CharacterOffsetEnd>94</CharacterOffsetEnd>
            <POS>NN</POS>
          </token>
          <token id="23">
            <word>vs</word>
            <lemma>vs</lemma>
            <CharacterOffsetBegin>95</CharacterOffsetBegin>
            <CharacterOffsetEnd>97</CharacterOffsetEnd>
            <POS>CC</POS>
          </token>
          <token id="24">
            <word>mln</word>
            <lemma>mln</lemma>
            <CharacterOffsetBegin>99</CharacterOffsetBegin>
            <CharacterOffsetEnd>102</CharacterOffsetEnd>
            <POS>NN</POS>
          </token>
          <token id="25">
            <word>Reuter</word>
            <lemma>Reuter</lemma>
            <CharacterOffsetBegin>104</CharacterOffsetBegin>
            <CharacterOffsetEnd>110</CharacterOffsetEnd>
            <POS>NNP</POS>
          </token>
          <token id="26">
            <word>3</word>
            <lemma>3</lemma>
            <CharacterOffsetBegin>111</CharacterOffsetBegin>
            <CharacterOffsetEnd>112</CharacterOffsetEnd>
            <POS>CD</POS>
          </token>
          <token id="27">
            <word>;</word>
            <lemma>;</lemma>
            <CharacterOffsetBegin>112</CharacterOffsetBegin>
            <CharacterOffsetEnd>113</CharacterOffsetEnd>
            <POS>:</POS>
          </token>
        </tokens>
      </sentence>
    </sentences>
  </document>
</root>
